{"actual_distance": 32, "positions": [{"fa_flight_id": null, "altitude": 17, "altitude_change": "C", "groundspeed": 130, "heading": 118, "latitude": 33.1215, "longitude": -97.75497, "timestamp": "2024-06-19T14:06:39Z", "update_type": "A"}, {"fa_flight_id": null, "altitude": 17, "altitude_change": "-", "groundspeed": 132, "heading": 125, "latitude": 33.10642, "longitude": -97.72916, "timestamp": "2024-06-19T14:07:22Z", "update_type": "A"}, {"fa_flight_id": null, "altitude": 17, "altitude_change": "-", "groundspeed": 135, "heading": 126, "latitude": 33.09359, "longitude": -97.70755, "timestamp": "2024-06-19T14:07:59Z", "update_type": "A"}, {"fa_flight_id": null, "altitude": 17, "altitude_change": "-", "groundspeed": 136, "heading": 124, "latitude": 33.0858, "longitude": -97.69393, "timestamp": "2024-06-19T14:08:20Z", "update_type": "A"}, {"fa_flight_id": null, "altitude": 17, "altitude_change": "-", "groundspeed": 135, "heading": 125, "latitude": 33.07752, "longitude": -97.67949, "timestamp": "2024-06-19T14:08:44Z", "update_type": "A"}, {"fa_flight_id": null, "altitude": 17, "altitude_change": "-", "groundspeed": 133, "heading": 124, "latitude": 33.07054, "longitude": -97.66708, "timestamp": "2024-06-19T14:09:04Z", "update_type": "A"}, {"fa_flight_id": null, "altitude": 17, "altitude_change": "-", "groundspeed": 133, "heading": 124, "latitude": 33.06368, "longitude": -97.65472, "timestamp": "2024-06-19T14:09:24Z", "update_type": "A"}, {"fa_flight_id": null, "altitude": 17, "altitude_change": "-", "groundspeed": 132, "heading": 128, "latitude": 33.05505, "longitude": -97.64123, "timestamp": "2024-06-19T14:09:47Z", "update_type": "A"}, {"fa_flight_id": null, "altitude": 17, "altitude_change": "-", "groundspeed": 131, "heading": 127, "latitude": 33.04754, "longitude": -97.62953, "timestamp": "2024-06-19T14:10:07Z", "update_type": "A"}, {"fa_flight_id": null, "altitude": 17, "altitude_change": "-", "groundspeed": 132, "heading": 127, "latitude": 33.04005, "longitude": -97.61797, "timestamp": "2024-06-19T14:10:27Z", "update_type": "A"}, {"fa_flight_id": null, "altitude": 17, "altitude_change": "-", "groundspeed": 133, "heading": 127, "latitude": 33.03263, "longitude": -97.60612, "timestamp": "2024-06-19T14:10:47Z", "update_type": "A"}, {"fa_flight_id": null, "altitude": 17, "altitude_change": "-", "groundspeed": 131, "heading": 127, "latitude": 33.02525, "longitude": -97.59447, "timestamp": "2024-06-19T14:11:07Z", "update_type": "A"}, {"fa_flight_id": null, "altitude": 17, "altitude_change": "-", "groundspeed": 131, "heading": 126, "latitude": 33.01778, "longitude": -97.58291, "timestamp": "2024-06-19T14:11:27Z", "update_type": "A"}, {"fa_flight_id": null, "altitude": 17, "altitude_change": "-", "groundspeed": 133, "heading": 126, "latitude": 33.01053, "longitude": -97.57121, "timestamp": "2024-06-19T14:11:47Z", "update_type": "A"}, {"fa_flight_id": null, "altitude": 17, "altitude_change": "-", "groundspeed": 136, "heading": 125, "latitude": 33.00681, "longitude": -97.5652, "timestamp": "2024-06-19T14:11:56Z", "update_type": "X"}, {"fa_flight_id": null, "altitude": 17, "altitude_change": "-", "groundspeed": 135, "heading": 127, "latitude": 33.00072, "longitude": -97.55559, "timestamp": "2024-06-19T14:12:12Z", "update_type": "A"}, {"fa_flight_id": null, "altitude": 17, "altitude_change": "-", "groundspeed": 133, "heading": 126, "latitude": 32.99175, "longitude": -97.54134, "timestamp": "2024-06-19T14:12:36Z", "update_type": "A"}, {"fa_flight_id": null, "altitude": 17, "altitude_change": "-", "groundspeed": 134, "heading": 129, "latitude": 32.98583, "longitude": -97.53181, "timestamp": "2024-06-19T14:12:52Z", "update_type": "A"}, {"fa_flight_id": null, "altitude": 17, "altitude_change": "-", "groundspeed": 135, "heading": 138, "latitude": 32.97935, "longitude": -97.52392, "timestamp": "2024-06-19T14:13:08Z", "update_type": "A"}, {"fa_flight_id": null, "altitude": 17, "altitude_change": "-", "groundspeed": 136, "heading": 137, "latitude": 32.97158, "longitude": -97.51521, "timestamp": "2024-06-19T14:13:24Z", "update_type": "A"}, {"fa_flight_id": null, "altitude": 17, "altitude_change": "-", "groundspeed": 134, "heading": 136, "latitude": 32.96255, "longitude": -97.50491, "timestamp": "2024-06-19T14:13:44Z", "update_type": "A"}, {"fa_flight_id": null, "altitude": 17, "altitude_change": "-", "groundspeed": 135, "heading": 136, "latitude": 32.95293, "longitude": -97.49396, "timestamp": "2024-06-19T14:14:05Z", "update_type": "A"}, {"fa_flight_id": null, "altitude": 17, "altitude_change": "-", "groundspeed": 134, "heading": 136, "latitude": 32.94388, "longitude": -97.48353, "timestamp": "2024-06-19T14:14:25Z", "update_type": "A"}, {"fa_flight_id": null, "altitude": 17, "altitude_change": "-", "groundspeed": 133, "heading": 134, "latitude": 32.9348, "longitude": -97.47291, "timestamp": "2024-06-19T14:14:45Z", "update_type": "A"}, {"fa_flight_id": null, "altitude": 17, "altitude_change": "-", "groundspeed": 132, "heading": 130, "latitude": 32.93188, "longitude": -97.46907, "timestamp": "2024-06-19T14:14:53Z", "update_type": "X"}, {"fa_flight_id": null, "altitude": 17, "altitude_change": "-", "groundspeed": 133, "heading": 129, "latitude": 32.92645, "longitude": -97.46107, "timestamp": "2024-06-19T14:15:07Z", "update_type": "A"}, {"fa_flight_id": null, "altitude": 17, "altitude_change": "-", "groundspeed": 132, "heading": 129, "latitude": 32.91862, "longitude": -97.44963, "timestamp": "2024-06-19T14:15:27Z", "update_type": "A"}, {"fa_flight_id": null, "altitude": 17, "altitude_change": "-", "groundspeed": 132, "heading": 129, "latitude": 32.91073, "longitude": -97.43828, "timestamp": "2024-06-19T14:15:47Z", "update_type": "A"}, {"fa_flight_id": null, "altitude": 17, "altitude_change": "-", "groundspeed": 135, "heading": 129, "latitude": 32.90313, "longitude": -97.42725, "timestamp": "2024-06-19T14:16:06Z", "update_type": "A"}, {"fa_flight_id": null, "altitude": 17, "altitude_change": "-", "groundspeed": 134, "heading": 129, "latitude": 32.89465, "longitude": -97.41498, "timestamp": "2024-06-19T14:16:27Z", "update_type": "A"}, {"fa_flight_id": null, "altitude": 17, "altitude_change": "-", "groundspeed": 135, "heading": 129, "latitude": 32.8879, "longitude": -97.40504, "timestamp": "2024-06-19T14:16:43Z", "update_type": "A"}, {"fa_flight_id": null, "altitude": 17, "altitude_change": "-", "groundspeed": 134, "heading": 131, "latitude": 32.88187, "longitude": -97.39622, "timestamp": "2024-06-19T14:16:59Z", "update_type": "A"}, {"fa_flight_id": null, "altitude": 16, "altitude_change": "D", "groundspeed": 120, "heading": 136, "latitude": 32.87485, "longitude": -97.38728, "timestamp": "2024-06-19T14:17:15Z", "update_type": "X"}, {"fa_flight_id": null, "altitude": 15, "altitude_change": "D", "groundspeed": 105, "heading": 141, "latitude": 32.86721, "longitude": -97.37921, "timestamp": "2024-06-19T14:17:35Z", "update_type": "A"}, {"fa_flight_id": null, "altitude": 13, "altitude_change": "D", "groundspeed": 103, "heading": 144, "latitude": 32.85996, "longitude": -97.37228, "timestamp": "2024-06-19T14:17:54Z", "update_type": "A"}, {"fa_flight_id": null, "altitude": 11, "altitude_change": "D", "groundspeed": 95, "heading": 162, "latitude": 32.85206, "longitude": -97.3665, "timestamp": "2024-06-19T14:18:14Z", "update_type": "A"}, {"fa_flight_id": null, "altitude": 9, "altitude_change": "D", "groundspeed": 93, "heading": 173, "latitude": 32.84575, "longitude": -97.36511, "timestamp": "2024-06-19T14:18:30Z", "update_type": "A"}, {"fa_flight_id": null, "altitude": 8, "altitude_change": "D", "groundspeed": 84, "heading": 170, "latitude": 32.83912, "longitude": -97.36391, "timestamp": "2024-06-19T14:18:46Z", "update_type": "A"}, {"fa_flight_id": null, "altitude": 6, "altitude_change": "D", "groundspeed": 79, "heading": 174, "latitude": 32.83279, "longitude": -97.36292, "timestamp": "2024-06-19T14:19:02Z", "update_type": "A"}]}