{"actual_distance": 28, "positions": [{"fa_flight_id": null, "altitude": 7, "altitude_change": "C", "groundspeed": 94, "heading": 171, "latitude": 32.81932, "longitude": -97.3606, "timestamp": "2024-08-02T01:06:15Z", "update_type": "A"}, {"fa_flight_id": null, "altitude": 10, "altitude_change": "C", "groundspeed": 98, "heading": 174, "latitude": 32.81209, "longitude": -97.3594, "timestamp": "2024-08-02T01:06:31Z", "update_type": "A"}, {"fa_flight_id": null, "altitude": 14, "altitude_change": "C", "groundspeed": 99, "heading": 178, "latitude": 32.80378, "longitude": -97.35846, "timestamp": "2024-08-02T01:06:47Z", "update_type": "A"}, {"fa_flight_id": null, "altitude": 17, "altitude_change": "C", "groundspeed": 104, "heading": 178, "latitude": 32.7958, "longitude": -97.35807, "timestamp": "2024-08-02T01:07:04Z", "update_type": "A"}, {"fa_flight_id": null, "altitude": 20, "altitude_change": "C", "groundspeed": 106, "heading": 178, "latitude": 32.78767, "longitude": -97.35751, "timestamp": "2024-08-02T01:07:21Z", "update_type": "A"}, {"fa_flight_id": null, "altitude": 23, "altitude_change": "C", "groundspeed": 101, "heading": 177, "latitude": 32.78044, "longitude": -97.35721, "timestamp": "2024-08-02T01:07:37Z", "update_type": "A"}, {"fa_flight_id": null, "altitude": 26, "altitude_change": "C", "groundspeed": 96, "heading": 172, "latitude": 32.77247, "longitude": -97.35644, "timestamp": "2024-08-02T01:07:53Z", "update_type": "A"}, {"fa_flight_id": null, "altitude": 28, "altitude_change": "C", "groundspeed": 98, "heading": 197, "latitude": 32.76526, "longitude": -97.35687, "timestamp": "2024-08-02T01:08:11Z", "update_type": "A"}, {"fa_flight_id": null, "altitude": 32, "altitude_change": "C", "groundspeed": 99, "heading": 195, "latitude": 32.75645, "longitude": -97.36, "timestamp": "2024-08-02T01:08:29Z", "update_type": "A"}, {"fa_flight_id": null, "altitude": 34, "altitude_change": "C", "groundspeed": 103, "heading": 195, "latitude": 32.74926, "longitude": -97.3623, "timestamp": "2024-08-02T01:08:46Z", "update_type": "A"}, {"fa_flight_id": null, "altitude": 34, "altitude_change": "-", "groundspeed": 130, "heading": 195, "latitude": 32.73859, "longitude": -97.36573, "timestamp": "2024-08-02T01:09:05Z", "update_type": "A"}, {"fa_flight_id": null, "altitude": 34, "altitude_change": "-", "groundspeed": 140, "heading": 194, "latitude": 32.71947, "longitude": -97.37187, "timestamp": "2024-08-02T01:09:36Z", "update_type": "A"}, {"fa_flight_id": null, "altitude": 34, "altitude_change": "-", "groundspeed": 143, "heading": 194, "latitude": 32.70677, "longitude": -97.37575, "timestamp": "2024-08-02T01:09:56Z", "update_type": "A"}, {"fa_flight_id": null, "altitude": 34, "altitude_change": "-", "groundspeed": 143, "heading": 195, "latitude": 32.69501, "longitude": -97.37934, "timestamp": "2024-08-02T01:10:15Z", "update_type": "A"}, {"fa_flight_id": null, "altitude": 34, "altitude_change": "-", "groundspeed": 142, "heading": 195, "latitude": 32.68079, "longitude": -97.38371, "timestamp": "2024-08-02T01:10:37Z", "update_type": "A"}, {"fa_flight_id": null, "altitude": 34, "altitude_change": "-", "groundspeed": 140, "heading": 194, "latitude": 32.66802, "longitude": -97.38766, "timestamp": "2024-08-02T01:10:57Z", "update_type": "A"}, {"fa_flight_id": null, "altitude": 34, "altitude_change": "-", "groundspeed": 138, "heading": 194, "latitude": 32.65551, "longitude": -97.3915, "timestamp": "2024-08-02T01:11:17Z", "update_type": "A"}, {"fa_flight_id": null, "altitude": 34, "altitude_change": "-", "groundspeed": 136, "heading": 194, "latitude": 32.64553, "longitude": -97.39444, "timestamp": "2024-08-02T01:11:33Z", "update_type": "A"}, {"fa_flight_id": null, "altitude": 34, "altitude_change": "-", "groundspeed": 135, "heading": 187, "latitude": 32.63055, "longitude": -97.39777, "timestamp": "2024-08-02T01:11:58Z", "update_type": "A"}, {"fa_flight_id": null, "altitude": 34, "altitude_change": "-", "groundspeed": 135, "heading": 187, "latitude": 32.61053, "longitude": -97.40045, "timestamp": "2024-08-02T01:12:29Z", "update_type": "A"}, {"fa_flight_id": null, "altitude": 34, "altitude_change": "-", "groundspeed": 133, "heading": 193, "latitude": 32.59637, "longitude": -97.40376, "timestamp": "2024-08-02T01:12:52Z", "update_type": "A"}, {"fa_flight_id": null, "altitude": 34, "altitude_change": "-", "groundspeed": 133, "heading": 189, "latitude": 32.57873, "longitude": -97.40833, "timestamp": "2024-08-02T01:13:20Z", "update_type": "A"}, {"fa_flight_id": null, "altitude": 34, "altitude_change": "-", "groundspeed": 134, "heading": 183, "latitude": 32.56318, "longitude": -97.40978, "timestamp": "2024-08-02T01:13:46Z", "update_type": "A"}, {"fa_flight_id": null, "altitude": 34, "altitude_change": "-", "groundspeed": 134, "heading": 186, "latitude": 32.5526, "longitude": -97.41049, "timestamp": "2024-08-02T01:14:04Z", "update_type": "A"}, {"fa_flight_id": null, "altitude": 32, "altitude_change": "D", "groundspeed": 139, "heading": 195, "latitude": 32.53374, "longitude": -97.415, "timestamp": "2024-08-02T01:14:33Z", "update_type": "A"}, {"fa_flight_id": null, "altitude": 31, "altitude_change": "D", "groundspeed": 138, "heading": 194, "latitude": 32.52438, "longitude": -97.41794, "timestamp": "2024-08-02T01:14:49Z", "update_type": "A"}, {"fa_flight_id": null, "altitude": 30, "altitude_change": "D", "groundspeed": 133, "heading": 194, "latitude": 32.51453, "longitude": -97.4209, "timestamp": "2024-08-02T01:15:05Z", "update_type": "A"}, {"fa_flight_id": null, "altitude": 29, "altitude_change": "D", "groundspeed": 129, "heading": 187, "latitude": 32.50372, "longitude": -97.42343, "timestamp": "2024-08-02T01:15:21Z", "update_type": "A"}, {"fa_flight_id": null, "altitude": 26, "altitude_change": "D", "groundspeed": 129, "heading": 182, "latitude": 32.48758, "longitude": -97.42446, "timestamp": "2024-08-02T01:15:49Z", "update_type": "A"}, {"fa_flight_id": null, "altitude": 23, "altitude_change": "D", "groundspeed": 132, "heading": 187, "latitude": 32.46509, "longitude": -97.42661, "timestamp": "2024-08-02T01:16:27Z", "update_type": "A"}, {"fa_flight_id": null, "altitude": 21, "altitude_change": "D", "groundspeed": 130, "heading": 192, "latitude": 32.45301, "longitude": -97.42916, "timestamp": "2024-08-02T01:16:46Z", "update_type": "A"}, {"fa_flight_id": null, "altitude": 18, "altitude_change": "D", "groundspeed": 125, "heading": 194, "latitude": 32.43018, "longitude": -97.43556, "timestamp": "2024-08-02T01:17:25Z", "update_type": "A"}, {"fa_flight_id": null, "altitude": 17, "altitude_change": "D", "groundspeed": 110, "heading": 192, "latitude": 32.42428, "longitude": -97.43731, "timestamp": "2024-08-02T01:17:36Z", "update_type": "X"}, {"fa_flight_id": null, "altitude": 15, "altitude_change": "D", "groundspeed": 86, "heading": 184, "latitude": 32.41821, "longitude": -97.43822, "timestamp": "2024-08-02T01:17:50Z", "update_type": "A"}]}